Flask_Sessionstore-0.4.5.dist-info/DESCRIPTION.rst
Flask_Sessionstore-0.4.5.dist-info/METADATA
Flask_Sessionstore-0.4.5.dist-info/RECORD
Flask_Sessionstore-0.4.5.dist-info/WHEEL
Flask_Sessionstore-0.4.5.dist-info/metadata.json
Flask_Sessionstore-0.4.5.dist-info/top_level.txt
flask_sessionstore/__init__.py
flask_sessionstore/sessions.py
