Metadata-Version: 1.1
Name: Flask-Sessionstore
Version: 0.4.5
Summary: Adds session support to your Flask application
Home-page: https://github.com/mcrowson/flask-sessionstore
Author: Matthew Crowson
Author-email: matthew.d.crowson@gmail.com
License: BSD
Platform: any
Classifier: Environment :: Web Environment
Classifier: Intended Audience :: Developers
Classifier: License :: OSI Approved :: BSD License
Classifier: Operating System :: OS Independent
Classifier: Programming Language :: Python :: 2
Classifier: Programming Language :: Python :: 3
Classifier: Topic :: Internet :: WWW/HTTP :: Dynamic Content
Classifier: Topic :: Software Development :: Libraries :: Python Modules
